MINI_RISC_PROPERLY.srcs/sources_1/new/parameters.v
parameter ADD = 5'b00000;
parameter MUL = 5'b00001;
parameter SUB = 5'b00010;
parameter DIV = 5'b00011;
parameter NOT = 5'b00100;
parameter AND = 5'b00101;
parameter OR = 5'b00110;
parameter XOR = 5'b00111;
parameter INC = 5'b01000;
parameter CMP = 5'b01001;
parameter RR = 5'b01010;
parameter RL = 5'b01011;
parameter SETB = 5'b01100;
parameter CLRB = 5'b01101;
parameter SETF = 5'b01110;

parameter ADDR_WIDTH = 11;  // adress is 11 bits
parameter DATA_WIDTH = 16;  // data is 16 bits
// 4Kb memory with 16 bit word size implies 2048 words (2^11)
parameter MEMORY_DEPTH = 2 ** ADDR_WIDTH;

parameter REG0 = 3'b000;
parameter REG1 = 3'b001;
parameter REG2 = 3'b010;
parameter REG3 = 3'b011;
parameter REG4 = 3'b100;
parameter REG5 = 3'b101;
parameter REG6 = 3'b110;
parameter REG7 = 3'b111;

MINI_RISC_PROPERLY.srcs/sources_1/new/ALU.v
module ALU (
    input wire clk,
    // input wire alu_en,
    input wire [4:0] opcode,  // from instruction register
    input wire [15:0] operand_1,  // reg_arg_2 in control unit
    input wire [15:0] operand_2,  // reg_arg_3 in control unit
    input wire [3:0] bit_position,  // set the bit in the postion given by this input
    output reg [15:0] result_0,  // to the data_in_0
    output reg [15:0] result_1,  // to the data_in_1
    output reg [15:0] flag_reg
);

  // The Bits of the flag Register
  /*
flag_reg[0] : Carry Flag (C)
flag_reg[1] : Overflow Flag (V)
flag_reg[2] : Compare Flag (CMP)
flag_reg[3] : Equal Flag (Eq)
flag_reg[4] : General Purpose Flag (F)
flag_reg[5] : Parity Flag (P) - Set when number of ones are even
flag_reg[6] : Negative Flag (N)
flag_reg[7] : Zero  Flag (Z)
*/
  `include "parameters.v"
  reg [31:0] mul_temp;
  reg [15:0] div_temp;
  reg [16:0] add_temp;

  // Function to calculate parity
  function automatic parity;
    input [15:0] value;
    begin
      parity = ~^value;  // XNOR reduction - 1 for even parity
    end
  endfunction

  // Common flag setting function
  task set_common_flags;
    input [15:0] value;
    begin

      flag_reg[7] <= (value == 16'b0);
      //Note: 6 and 5 used to be = not <=
      flag_reg[6] <= value[15];
      flag_reg[5] <= parity(value);
    end
  endtask

  always @(posedge clk) begin
    // Default flag values
    {flag_reg[0], flag_reg[1], flag_reg[2], flag_reg[3], flag_reg[4], 
      flag_reg[5], flag_reg[6], flag_reg[7]} = 8'b0;
    case (opcode)
      ADD: begin
        add_temp = {1'b0, operand_1} + {1'b0, operand_2};
        result_0 = add_temp[15:0];

        // Flag settings
        flag_reg[0] = add_temp[16];
        flag_reg[1] = (operand_1[15] == operand_2[15]) && (result_0[15] != operand_1[15]);
        set_common_flags(result_0);
      end
      MUL: begin
        mul_temp = operand_1 * operand_2;
        result_0 = mul_temp[15:0];
        // TODO: the write_en should change to 11
        result_1 = mul_temp[31:16];
        flag_reg[0] = 0;
      end
      SUB: begin
        result_0 = operand_1 - operand_2;

        // Flag settings
        flag_reg[0] = (operand_1 < operand_2);
        flag_reg[1] = (operand_1[15] != operand_2[15]) && (result_0[15] == operand_2[15]);
        set_common_flags(result_0);
      end
      DIV: begin
        if (operand_2 != 0) begin
          result_0 = operand_1 / operand_2;
          // TODO: the write_en should change to 11
          result_1 = operand_1 % operand_2;

          // Flag settings
          set_common_flags(result_0);
        end else begin
          result_0 = 16'hFFFF;
          flag_reg[1] = 1'b1;
        end
      end

      NOT: begin
        result_0 = ~operand_1;
        set_common_flags(result_0);
      end

      AND: begin
        result_0 = operand_1 & operand_2;
        set_common_flags(result_0);
      end

      OR: begin
        result_0 = operand_1 | operand_2;
        set_common_flags(result_0);
      end

      XOR: begin
        result_0 = operand_1 ^ operand_2;
        set_common_flags(result_0);
      end

      INC: begin
        add_temp = {1'b0, operand_1} + 16'b1;
        result_0 = add_temp[15:0];
        // Flag settings
        flag_reg[0] = add_temp[16];
        flag_reg[1] = (operand_1[15] == 1'b0) && (result_0[15] == 1'b1);
        set_common_flags(result_0);
      end

      CMP: begin
        result_0 = operand_1 - operand_2;
        // Flag settings
        flag_reg[2] = (operand_1 > operand_2);
        flag_reg[3] = (operand_1 == operand_2);
        flag_reg[0] = (operand_1 < operand_2);
        set_common_flags(result_0);
      end

      RR: begin
        result_0 = {operand_1[0], operand_1[15:1]};
        set_common_flags(result_0);
      end

      RL: begin
        result_0 = {operand_1[14:0], operand_1[15]};
        set_common_flags(result_0);
      end

      SETB: begin
        result_0 = operand_1 | (16'b1 << bit_position);
        set_common_flags(result_0);
      end

      CLRB: begin
        result_0 = operand_1 & ~(16'b1 << bit_position);
        set_common_flags(result_0);
      end
      SETF: begin
        flag_reg[bit_position] = 1'b1;
      end
      default: $display("No operation");
    endcase
  end
endmodule

MINI_RISC_PROPERLY.srcs/sources_1/new/ALU_tb.v
`timescale 1ns / 1ps
//////////////////////////////////////////////////////////////////////////////////
// Company: 
// Engineer: 
// 
// Create Date: 13.02.2025 11:47:45
// Design Name: 
// Module Name: ALU_tb
// Project Name: 
// Target Devices: 
// Tool Versions: 
// Description: 
// 
// Dependencies: 
// 
// Revision:
// Revision 0.01 - File Created
// Additional Comments:
// 
//////////////////////////////////////////////////////////////////////////////////

module ALU_tb();
    // Inputs
    reg clk;
    reg [4:0] opcode;
    reg [15:0] operand_1;
    reg [15:0] operand_2;
    reg [3:0] bit_position;
    
    // Outputs
    wire [15:0] result_0;
    wire [15:0] result_1;
    wire [15:0] flag_reg;
   
    ALU dut (
        .clk(clk),
        .opcode(opcode),
        .operand_1(operand_1),
        .operand_2(operand_2),
        .bit_position(bit_position),
        .result_0(result_0),
        .result_1(result_1),
        .flag_reg(flag_reg)
    );
   

    integer num_failures;
    // Clock generation
    initial begin
        num_failures = 0;
        clk = 0;
        forever #5 clk = ~clk;
    end
    
    // Test stimulus
    initial begin
        // Initialize inputs
        opcode = 0;
        operand_1 = 0;
        operand_2 = 0;
        bit_position = 0;
        
        // Wait for 100 ns for global reset
        #100;
        

	/* Syntax: test_case (input [64:0] test_name; input [4:0] test_opcode; 
			      input [15:0] test_op1; input [15:0] test_op2; input [3:0] test_bit_pos;) */
        // Test ADD operation
        // Normal addition
        test_case("ADD - Normal", 5'b00000, 16'd10, 16'd20, 4'd0);
        // Addition with carry
        test_case("ADD - Carry", 5'b00000, 16'hFFFF, 16'd1, 4'd0);
        // Addition with overflow
        test_case("ADD - Overflow", 5'b00000, 16'h7FFF, 16'h7FFF, 4'd0);
        
        // Test MUL operation
        test_case("MUL - Normal", 5'b00001, 16'd10, 16'd20, 4'd0);
        test_case("MUL - Large", 5'b00001, 16'hFFFF, 16'h2, 4'd0);
        
        // Test SUB operation
        test_case("SUB - Normal", 5'b00010, 16'd20, 16'd10, 4'd0);
        test_case("SUB - Negative", 5'b00010, 16'd40, 16'd29, 4'd0);
        
        // Test DIV operation
        test_case("DIV - Normal", 5'b00011, 16'd20, 16'd5, 4'd0);
        test_case("DIV - By Zero", 5'b00011, 16'd20, 16'd0, 4'd0);
        
        // Test logical operations
        test_case("NOT", 5'b00100, 16'hAAAA, 16'd0, 4'd0);
        test_case("AND", 5'b00101, 16'hAAAA, 16'h5555, 4'd0);
        test_case("OR", 5'b00110, 16'hAAAA, 16'h5555, 4'd0);
        test_case("XOR", 5'b00111, 16'hAAAA, 16'h5555, 4'd0);
        
        // Test INC operation
        test_case("INC - Normal", 5'b01000, 16'd10, 16'd0, 4'd0);
        test_case("INC - Overflow", 5'b01000, 16'hFFFF, 16'd0, 4'd0);
        
        // Test CMP operation
        test_case("CMP - Equal", 5'b01001, 16'd10, 16'd10, 4'd0);
        test_case("CMP - Greater", 5'b01001, 16'd20, 16'd10, 4'd0);
        test_case("CMP - Less", 5'b01001, 16'd10, 16'd20, 4'd0);
        
        // Test rotation operations
        test_case("RR", 5'b01010, 16'hAAAA, 16'd0, 4'd0);
        test_case("RL", 5'b01011, 16'hAAAA, 16'd0, 4'd0);
        
        // Test bit operations
        test_case("SETB", 5'b01100, 16'h0000, 16'd0, 4'd8);
        test_case("CLRB", 5'b01101, 16'hFFFF, 16'd0, 4'd8);

        // Test setting different flag bits
        test_case("SETF - Carry Flag", 5'b01110, 16'h0000, 16'h0000, 4'd0);
        test_case("SETF - Zero Flag", 5'b01110, 16'h0000, 16'h0000, 4'd7);
        test_case("SETF - Negative Flag", 5'b01110, 16'h0000, 16'h0000, 4'd6);
        test_case("SETF - General Purpose Flag", 5'b01110, 16'h0000, 16'h0000, 4'd4);
        
        $display("\n=== Test Summary ===");
        if (num_failures == 0)
            $display("All tests passed successfully!");
        else
            $display("Some tests failed.");
        // End simulation
        #100 $finish;
    end
    
    // Task to run test cases
    task test_case;
        input [255:0] test_name;
        input [4:0] test_opcode;
        input [15:0] test_op1;
        input [15:0] test_op2;
        input [3:0] test_bit_pos;
        reg failed;
        reg [31:0] expected_mul;
        reg [15:0] expected_div, expected_mod;
        begin
            failed = 0;
            $display("\nRunning test: %s", test_name);
            @(negedge clk);
            opcode = test_opcode;
            operand_1 = test_op1;
            operand_2 = test_op2;
            bit_position = test_bit_pos;
            
            @(posedge clk);
            #1; // Wait for outputs to stabilize
            case(test_opcode)
                5'b00000: begin // ADD
                    if(result_0 !== test_op1 + test_op2) begin
                        failed = 1;
                        $display("\nFAILURE in %s:", test_name);
                        $display("ADD operation failed:");
                        $display("Expected: %h, Got: %h", test_op1 + test_op2, result_0);
                        $display("Carry flag: %b", flag_reg[0]);
                    end
                end
                
                5'b00001: begin // MUL
                    expected_mul = test_op1 * test_op2;
                    if(result_0 !== expected_mul[15:0] || result_1 !== expected_mul[31:16]) begin
                        failed = 1;
                        $display("\nFAILURE in %s:", test_name);
                        $display("MUL operation failed:");
                        $display("Expected: %h%h, Got: %h%h", expected_mul[31:16], expected_mul[15:0], result_1, result_0);
                    end
                end
                
                5'b00010: begin // SUB
                    if(result_0 !== test_op1 - test_op2) begin
                        failed = 1;
                        $display("\nFAILURE in %s:", test_name);
                        $display("SUB operation failed:");
                        $display("Expected: %h, Got: %h", test_op1 - test_op2, result_0);
                        $display("Borrow flag: %b", flag_reg[0]);
                    end
                end
                
                5'b00011: begin // DIV
                    if(test_op2 != 0) begin
                        expected_div = test_op1 / test_op2;
                        expected_mod = test_op1 % test_op2;
                        if(result_0 !== expected_div || result_1 !== expected_mod) begin
                            failed = 1;
                            $display("\nFAILURE in %s:", test_name);
                            $display("DIV operation failed:");
                            $display("Expected quotient: %h, Got: %h", expected_div, result_0);
                            $display("Expected remainder: %h, Got: %h", expected_mod, result_1);
                        end
                    end else if(result_0 !== 16'hFFFF || !flag_reg[1]) begin
                        failed = 1;
                        $display("\nFAILURE in %s:", test_name);
                        $display("DIV by zero handling failed");
                    end
                end
                
                5'b00100: begin // NOT
                    if(result_0 !== ~test_op1) begin
                        failed = 1;
                        $display("\nFAILURE in %s:", test_name);
                        $display("NOT operation failed:");
                        $display("Expected: %h, Got: %h", ~test_op1, result_0);
                    end
                end
                
                5'b00101: begin // AND
                    if(result_0 !== (test_op1 & test_op2)) begin
                        failed = 1;
                        $display("\nFAILURE in %s:", test_name);
                        $display("AND operation failed:");
                        $display("Expected: %h, Got: %h", test_op1 & test_op2, result_0);
                    end
                end
                
                5'b00110: begin // OR
                    if(result_0 !== (test_op1 | test_op2)) begin
                        failed = 1;
                        $display("\nFAILURE in %s:", test_name);
                        $display("OR operation failed:");
                        $display("Expected: %h, Got: %h", test_op1 | test_op2, result_0);
                    end
                end
                
                5'b00111: begin // XOR
                    if(result_0 !== (test_op1 ^ test_op2)) begin
                        failed = 1;
                        $display("\nFAILURE in %s:", test_name);
                        $display("XOR operation failed:");
                        $display("Expected: %h, Got: %h", test_op1 ^ test_op2, result_0);
                    end
                end
                
                5'b01000: begin // INC
                    if(result_0 !== test_op1 + 16'h0001) begin
                        failed = 1;
                        $display("\nFAILURE in %s:", test_name);
                        $display("INC operation failed:");
                        $display("Expected: %h, Got: %h", test_op1 + 16'h0001, result_0);
                        $display("Overflow flag: %b", flag_reg[1]);
                    end
                end
                
                5'b01001: begin // CMP
                    if((test_op1 == test_op2 && !flag_reg[3]) ||
                       (test_op1 > test_op2 && !flag_reg[2]) ||
                       (test_op1 < test_op2 && !flag_reg[0])) begin
                        failed = 1;
                        $display("\nFAILURE in %s:", test_name);
                        $display("CMP flags incorrect:");
                        $display("Expected: Equal=%b, Greater=%b, Less=%b",
                               test_op1 == test_op2,
                               test_op1 > test_op2,
                               test_op1 < test_op2);
                        $display("Got flags: %b", flag_reg);
                    end
                end
                
                5'b01010: begin // RR
                    if(result_0 !== {test_op1[0], test_op1[15:1]}) begin
                        failed = 1;
                        $display("\nFAILURE in %s:", test_name);
                        $display("RR operation failed:");
                        $display("Expected: %h, Got: %h", {test_op1[0], test_op1[15:1]}, result_0);
                    end
                end
                
                5'b01011: begin // RL
                    if(result_0 !== {test_op1[14:0], test_op1[15]}) begin
                        failed = 1;
                        $display("\nFAILURE in %s:", test_name);
                        $display("RL operation failed:");
                        $display("Expected: %h, Got: %h", {test_op1[14:0], test_op1[15]}, result_0);
                    end
                end
                
                5'b01100: begin // SETB
                    if(result_0 !== (test_op1 | (16'b1 << test_bit_pos))) begin
                        failed = 1;
                        $display("\nFAILURE in %s:", test_name);
                        $display("SETB operation failed:");
                        $display("Expected: %h, Got: %h", test_op1 | (16'b1 << test_bit_pos), result_0);
                    end
                end
                
                5'b01101: begin // CLRB
                    if(result_0 !== (test_op1 & ~(16'b1 << test_bit_pos))) begin
                        failed = 1;
                        $display("\nFAILURE in %s:", test_name);
                        $display("CLRB operation failed:");
                        $display("Expected: %h, Got: %h", test_op1 & ~(16'b1 << test_bit_pos), result_0);
                    end
                end
                
                5'b01110: begin // SETF
                    if(!flag_reg[test_bit_pos]) begin
                        failed = 1;
                        $display("\nFAILURE in %s:", test_name);
                        $display("SETF operation failed:");
                        $display("Flag bit %d not set", test_bit_pos);
                    end
                end
                
                5'b01111: begin // SWAP
                    if(result_0 !== {test_op1[7:0], test_op1[15:8]}) begin
                        failed = 1;
                        $display("\nFAILURE in %s:", test_name);
                        $display("SWAP operation failed:");
                        $display("Expected: %h, Got: %h", {test_op1[7:0], test_op1[15:8]}, result_0);
                    end
                end
            endcase
            
                if(failed) begin
                  num_failures = num_failures + 1;
                end
        end
    endtask
    
    // Wave dump
    initial begin
        $dumpfile("alu_test.vcd");
        $dumpvars(0, ALU_tb);
    end
    
endmodule

MINI_RISC_PROPERLY.sim/sim_1/behav/xsim/alu_test.vcd
$date
   Sun Feb 16 15:48:41 2025
$end

$version
  2024.2.0
  $dumpfile ("alu_test.vcd") 
$end

$timescale
  1ps
$end

$scope module ALU_tb $end
$var reg 1 ! clk $end
$var reg 5 " opcode [4:0] $end
$var reg 16 # operand_1 [15:0] $end
$var reg 16 $ operand_2 [15:0] $end
$var reg 4 % bit_position [3:0] $end
$var wire 16 & result_0 [15:0] $end
$var wire 16 ' result_1 [15:0] $end
$var wire 16 ( flag_reg [15:0] $end
$var integer 32 ) num_failures [31:0] $end
$scope module dut $end
$var wire 1 * clk $end
$var wire 5 + opcode [4:0] $end
$var wire 16 , operand_1 [15:0] $end
$var wire 16 - operand_2 [15:0] $end
$var wire 4 . bit_position [3:0] $end
$var reg 16 / result_0 [15:0] $end
$var reg 16 0 result_1 [15:0] $end
$var reg 16 1 flag_reg [15:0] $end
$var reg 32 2 mul_temp [31:0] $end
$var reg 16 3 div_temp [15:0] $end
$var reg 17 4 add_temp [16:0] $end
$scope function parity $end
$upscope $end
$scope task set_common_flags $end
$var reg 16 5 value [15:0] $end
$upscope $end
$upscope $end
$scope task test_case $end
$var reg 256 6 test_name [255:0] $end
$var reg 5 7 test_opcode [4:0] $end
$var reg 16 8 test_op1 [15:0] $end
$var reg 16 9 test_op2 [15:0] $end
$var reg 4 : test_bit_pos [3:0] $end
$var reg 1 ; failed $end
$var reg 32 < expected_mul [31:0] $end
$var reg 16 = expected_div [15:0] $end
$var reg 16 > expected_mod [15:0] $end
$upscope $end
$upscope $end
$enddefinitions $end

#0
$dumpvars
0!
b0 "
b0 #
b0 $
b0 %
bx &
bx '
bx (
b0 )
0*
b0 +
b0 ,
b0 -
b0 .
bx /
bx 0
bx 1
bx 2
bx 3
bx 4
bx 5
bx 6
bx 7
bx 8
bx 9
bx :
x;
bx <
bx =
bx >
$end

#5000
1!
b0 &
bx10100000 (
1*
b0 /
bx10100000 1
b0 4
b0 5

#10000
0!
0*

#15000
1!
bx10100000 (
1*
bx10100000 1

#20000
0!
0*

#25000
1!
bx10100000 (
1*
bx10100000 1

#30000
0!
0*

#35000
1!
bx10100000 (
1*
bx10100000 1

#40000
0!
0*

#45000
1!
bx10100000 (
1*
bx10100000 1

#50000
0!
0*

#55000
1!
bx10100000 (
1*
bx10100000 1

#60000
0!
0*

#65000
1!
bx10100000 (
1*
bx10100000 1

#70000
0!
0*

#75000
1!
bx10100000 (
1*
bx10100000 1

#80000
0!
0*

#85000
1!
bx10100000 (
1*
bx10100000 1

#90000
0!
0*

#95000
1!
bx10100000 (
1*
bx10100000 1

#100000
0!
b1010 #
b10100 $
0*
b1010 ,
b10100 -
b10000010100010001000100001000000010110100100000010011100110111101110010011011010110000101101100 6
b0 7
b1010 8
b10100 9
b0 :
0;

#105000
1!
b11110 &
bx00100000 (
1*
b11110 /
bx00100000 1
b11110 4
b11110 5

#106000
b100000101000100010001000010000000101101001000000100001101100001011100100111001001111001 6
b1111111111111111 8
b1 9

#110000
0!
b1111111111111111 #
b1 $
0*
b1111111111111111 ,
b1 -

#115000
1!
b0 &
bx10100001 (
1*
b0 /
bx10100001 1
b10000000000000000 4
b0 5

#116000
b100000101000100010001000010000000101101001000000100111101110110011001010111001001100110011011000110111101110111 6
b111111111111111 8
b111111111111111 9

#120000
0!
b111111111111111 #
b111111111111111 $
0*
b111111111111111 ,
b111111111111111 -

#125000
1!
b1111111111111110 &
bx01000010 (
1*
b1111111111111110 /
bx01000010 1
b1111111111111110 4
b1111111111111110 5

#126000
b10011010101010101001100001000000010110100100000010011100110111101110010011011010110000101101100 6
b1 7
b1010 8
b10100 9

#130000
0!
b1 "
b1010 #
b10100 $
0*
b1 +
b1010 ,
b10100 -

#135000
1!
b11001000 &
b0 '
bx00000000 (
1*
b11001000 /
b0 0
bx00000000 1
b11001000 2

#136000
b100110101010101010011000010000000101101001000000100110001100001011100100110011101100101 6
b1111111111111111 8
b10 9
b11001000 <

#140000
0!
b1111111111111111 #
b10 $
0*
b1111111111111111 ,
b10 -

#145000
1!
b1111111111111110 &
b1 '
1*
b1111111111111110 /
b1 0
b11111111111111110 2

#146000
b10100110101010101000010001000000010110100100000010011100110111101110010011011010110000101101100 6
b10 7
b10100 8
b1010 9
b11111111111111110 <

#150000
0!
b10 "
b10100 #
b1010 $
0*
b10 +
b10100 ,
b1010 -

#155000
1!
b1010 &
bx00100000 (
1*
b1010 /
bx00100000 1
b1010 5

#156000
b101001101010101010000100010000000101101001000000100111001100101011001110110000101110100011010010111011001100101 6
b101000 8
b11101 9

#160000
0!
b101000 #
b11101 $
0*
b101000 ,
b11101 -

#165000
1!
b1011 &
bx00000000 (
1*
b1011 /
bx00000000 1
b1011 5

#166000
b10001000100100101010110001000000010110100100000010011100110111101110010011011010110000101101100 6
b11 7
b10100 8
b101 9

#170000
0!
b11 "
b10100 #
b101 $
0*
b11 +
b10100 ,
b101 -

#175000
1!
b100 &
b0 '
1*
b100 /
b0 0
b100 5

#176000
b1000100010010010101011000100000001011010010000001000010011110010010000001011010011001010111001001101111 6
b0 9
b100 =
b0 >

#180000
0!
b0 $
0*
b0 -

#185000
1!
b1111111111111111 &
bx00000010 (
1*
b1111111111111111 /
bx00000010 1

#186000
b10011100100111101010100 6
b100 7
b1010101010101010 8

#190000
0!
b100 "
b1010101010101010 #
0*
b100 +
b1010101010101010 ,

#195000
1!
b101010101010101 &
bx00100000 (
1*
b101010101010101 /
bx00100000 1
b101010101010101 5

#196000
b10000010100111001000100 6
b101 7
b101010101010101 9

#200000
0!
b101 "
b101010101010101 $
0*
b101 +
b101010101010101 -

#205000
1!
b0 &
bx10100000 (
1*
b0 /
bx10100000 1
b0 5

#206000
b100111101010010 6
b110 7

#210000
0!
b110 "
0*
b110 +

#215000
1!
b1111111111111111 &
bx01100000 (
1*
b1111111111111111 /
bx01100000 1
b1111111111111111 5

#216000
b10110000100111101010010 6
b111 7

#220000
0!
b111 "
0*
b111 +

#225000
1!
bx01100000 (
1*
bx01100000 1

#226000
b10010010100111001000011001000000010110100100000010011100110111101110010011011010110000101101100 6
b1000 7
b1010 8
b0 9

#230000
0!
b1000 "
b1010 #
b0 $
0*
b1000 +
b1010 ,
b0 -

#235000
1!
b1011 &
bx00000000 (
1*
b1011 /
bx00000000 1
b1011 4
b1011 5

#236000
b100100101001110010000110010000000101101001000000100111101110110011001010111001001100110011011000110111101110111 6
b1111111111111111 8

#240000
0!
b1111111111111111 #
0*
b1111111111111111 ,

#245000
1!
b0 &
bx10100001 (
1*
b0 /
bx10100001 1
b10000000000000000 4
b0 5

#246000
b100001101001101010100000010000000101101001000000100010101110001011101010110000101101100 6
b1001 7
b1010 8
b1010 9

#250000
0!
b1001 "
b1010 #
b1010 $
0*
b1001 +
b1010 ,
b1010 -

#255000
1!
bx10101000 (
1*
bx10101000 1

#256000
b1000011010011010101000000100000001011010010000001000111011100100110010101100001011101000110010101110010 6
b10100 8

#260000
0!
b10100 #
0*
b10100 ,

#265000
1!
b1010 &
bx00100100 (
1*
b1010 /
bx00100100 1
b1010 5

#266000
b1000011010011010101000000100000001011010010000001001100011001010111001101110011 6
b1010 8
b10100 9

#270000
0!
b1010 #
b10100 $
0*
b1010 ,
b10100 -

#275000
1!
b1111111111110110 &
bx01100001 (
1*
b1111111111110110 /
bx01100001 1
b1111111111110110 5

#276000
b101001001010010 6
b1010 7
b1010101010101010 8
b0 9

#280000
0!
b1010 "
b1010101010101010 #
b0 $
0*
b1010 +
b1010101010101010 ,
b0 -

#285000
1!
b101010101010101 &
bx00100000 (
1*
b101010101010101 /
bx00100000 1
b101010101010101 5

#286000
b101001001001100 6
b1011 7

#290000
0!
b1011 "
0*
b1011 +

#295000
1!
bx00100000 (
1*
bx00100000 1

#296000
b1010011010001010101010001000010 6
b1100 7
b0 8
b1000 :

#300000
0!
b1100 "
b0 #
b1000 %
0*
b1100 +
b0 ,
b1000 .

#305000
1!
b100000000 &
bx00000000 (
1*
b100000000 /
bx00000000 1
b100000000 5

#306000
b1000011010011000101001001000010 6
b1101 7
b1111111111111111 8

#310000
0!
b1101 "
b1111111111111111 #
0*
b1101 +
b1111111111111111 ,

#315000
1!
b1111111011111111 &
bx01000000 (
1*
b1111111011111111 /
bx01000000 1
b1111111011111111 5

#316000
b101001101000101010101000100011000100000001011010010000001000011011000010111001001110010011110010010000001000110011011000110000101100111 6
b1110 7
b0 8
b0 :

#320000
0!
b1110 "
b0 #
b0 %
0*
b1110 +
b0 ,
b0 .

#325000
1!
bx00000001 (
1*
bx00000001 1

#326000
b1010011010001010101010001000110001000000010110100100000010110100110010101110010011011110010000001000110011011000110000101100111 6
b111 :

#330000
0!
b111 %
0*
b111 .

#335000
1!
bx10000000 (
1*
bx10000000 1

#336000
b101001101000101010101000100011000100000001011010010000001001110011001010110011101100001011101000110100101110110011001010010000001000110011011000110000101100111 6
b110 :

#340000
0!
b110 %
0*
b110 .

#345000
1!
bx01000000 (
1*
bx01000000 1

#346000
b10100110100010101010100010001100010000000101101001000000100011101100101011011100110010101110010011000010110110000100000010100000111010101110010011100000110111101110011011001010010000001000110011011000110000101100111 6
b100 :

#350000
0!
b100 %
0*
b100 .

#355000
1!
bx00010000 (
1*
bx00010000 1

#360000
0!
0*

#365000
1!
1*
bx00010000 1

#370000
0!
0*

#375000
1!
1*
bx00010000 1

#380000
0!
0*

#385000
1!
1*
bx00010000 1

#390000
0!
0*

#395000
1!
1*
bx00010000 1

#400000
0!
0*

#405000
1!
1*
bx00010000 1

#410000
0!
0*

#415000
1!
1*
bx00010000 1

#420000
0!
0*

#425000
1!
1*
bx00010000 1

#430000
0!
0*

#435000
1!
1*
bx00010000 1

#440000
0!
0*

#445000
1!
1*
bx00010000 1

#450000
0!
0*

#455000
1!
1*
bx00010000 1
